bayesclass/__init__.py
bayesclass/_version.py
bayesclass/clfs.py
bayesclass/tests/__init__.py
bayesclass/tests/test_AODE.py
bayesclass/tests/test_KDB.py
bayesclass/tests/test_TAN.py
bayesclass/tests/test_common.py
bayesclass/tests/baseline_images/test_AODE/line_dashes_AODE.png
bayesclass/tests/baseline_images/test_KDB/line_dashes_KDB.png
bayesclass/tests/baseline_images/test_TAN/line_dashes_TAN.png
bayesclass-0.1.0.dist-info/LICENSE
bayesclass-0.1.0.dist-info/METADATA
bayesclass-0.1.0.dist-info/WHEEL
bayesclass-0.1.0.dist-info/top_level.txt
bayesclass-0.1.0.dist-info/RECORD
